OauthWarden/__init__.py
OauthWarden/warden.py
OauthWarden-0.0.2.dist-info/LICENSE.txt
OauthWarden-0.0.2.dist-info/METADATA
OauthWarden-0.0.2.dist-info/WHEEL
OauthWarden-0.0.2.dist-info/top_level.txt
OauthWarden-0.0.2.dist-info/RECORD
